WikidPad/Consts.py
WikidPad/Consts.py~
WikidPad/ExceptionLogger.py
WikidPad/WikidPad (copy).xrc__
WikidPad/WikidPad (copy).xrc___
WikidPad/WikidPad.pot
WikidPad/WikidPad.py
WikidPad/WikidPad.xrc
WikidPad/WikidPad.xrc~
WikidPad/WikidPadStarter.py
WikidPad/WikidPadStarter.py~
WikidPad/WikidPad_hu_HU.po
WikidPad/WikidPad_ru_RU.po
WikidPad/WikidPad_sv.po
WikidPad/WikidPad_zh_CN.po
WikidPad/WikidPad_zh_TW.po
WikidPad/Wikidpad.icns
WikidPad/Wikidpad_128x128x32.png
WikidPad/Wikidpad_16x16x32.png
WikidPad/Wikidpad_256x256x32.png
WikidPad/Wikidpad_32x32x32.png
WikidPad/Wikidpad_512x512x32.png
WikidPad/__init__.py
WikidPad/__main__.py
WikidPad/appbase.css
WikidPad/langlist.txt
WikidPad/license-spelladdon.txt
WikidPad/license.txt
WikidPad/msgfmt.py
WikidPad/pygettext.py
WikidPad/updateI18N.py
WikidPad/wikidpad.ico
WikidPad/WikidPadHelp/WikidPadHelp.wiki
WikidPad/WikidPadHelp/data/ACLs.wiki
WikidPad/WikidPadHelp/data/ADSs.wiki
WikidPad/WikidPadHelp/data/Anchors.wiki
WikidPad/WikidPadHelp/data/ApiDocs.wiki
WikidPad/WikidPadHelp/data/ApplicationConfigurationFiles.wiki
WikidPad/WikidPadHelp/data/ArticleFoobaromatic.wiki
WikidPad/WikidPadHelp/data/AutoCompletion.wiki
WikidPad/WikidPadHelp/data/AutoSave.wiki
WikidPad/WikidPadHelp/data/BoughtTemplate.wiki
WikidPad/WikidPadHelp/data/BulletedLists.wiki
WikidPad/WikidPadHelp/data/CamelCase.wiki
WikidPad/WikidPadHelp/data/Cascading style sheets.wiki
WikidPad/WikidPadHelp/data/ChangeFileSuffix.wiki
WikidPad/WikidPadHelp/data/ChangeLog.wiki
WikidPad/WikidPadHelp/data/ChangeLog2003.wiki
WikidPad/WikidPadHelp/data/ChangeLog2004.wiki
WikidPad/WikidPadHelp/data/ChangeLog2005.wiki
WikidPad/WikidPadHelp/data/ChangeLog2006.wiki
WikidPad/WikidPadHelp/data/ChangeLog2007.wiki
WikidPad/WikidPadHelp/data/ChangeLog2008.wiki
WikidPad/WikidPadHelp/data/ChangeLog2009.wiki
WikidPad/WikidPadHelp/data/ChangeLog2010.wiki
WikidPad/WikidPadHelp/data/ChangeLog2011.wiki
WikidPad/WikidPadHelp/data/ChangingKeyBindings.wiki
WikidPadMP-2.4a1.dev5.dist-info/METADATA
WikidPadMP-2.4a1.dev5.dist-info/WHEEL
WikidPadMP-2.4a1.dev5.dist-info/entry_points.txt
WikidPadMP-2.4a1.dev5.dist-info/top_level.txt
WikidPadMP-2.4a1.dev5.dist-info/RECORD
