Metadata-Version: 2.1
Name: WikidPadMP
Version: 2.4a1.dev5
Summary: Single user wiki notepad
Home-page: http://wikidpad.sourceforge.net/
Author: Michael Butscher
Author-email: mbutscher@gmx.de
Keywords: Personal Wiki
Classifier: Development Status :: 3 - Alpha
Classifier: Intended Audience :: End Users/Desktop
Classifier: Operating System :: OS Independent
Classifier: License :: OSI Approved :: BSD License
Classifier: Programming Language :: Python :: 3.8
Classifier: Topic :: Office/Business
Requires-Dist: wxPython
